<annotation>
	<folder>Images</folder>
	<filename>425.jpg</filename>
	<path>/Users/meblang/Desktop/shoe_dataset/Images/425.jpg</path>
	<source>
		<database>Unknown</database>
	</source>
	<size>
		<width>3840</width>
		<height>2160</height>
		<depth>3</depth>
	</size>
	<segmented>0</segmented>
	<object>
		<name>shoe</name>
		<pose>Unspecified</pose>
		<truncated>0</truncated>
		<difficult>0</difficult>
		<bndbox>
			<xmin>357</xmin>
			<ymin>1228</ymin>
			<xmax>572</xmax>
			<ymax>1424</ymax>
		</bndbox>
	</object>
	<object>
		<name>shoe</name>
		<pose>Unspecified</pose>
		<truncated>0</truncated>
		<difficult>0</difficult>
		<bndbox>
			<xmin>783</xmin>
			<ymin>968</ymin>
			<xmax>1049</xmax>
			<ymax>1428</ymax>
		</bndbox>
	</object>
</annotation>