<annotation>
	<folder>Images</folder>
	<filename>434.jpg</filename>
	<path>/Users/meblang/Desktop/shoe_dataset/Images/434.jpg</path>
	<source>
		<database>Unknown</database>
	</source>
	<size>
		<width>3840</width>
		<height>2160</height>
		<depth>3</depth>
	</size>
	<segmented>0</segmented>
	<object>
		<name>shoe</name>
		<pose>Unspecified</pose>
		<truncated>0</truncated>
		<difficult>0</difficult>
		<bndbox>
			<xmin>735</xmin>
			<ymin>953</ymin>
			<xmax>1216</xmax>
			<ymax>1198</ymax>
		</bndbox>
	</object>
	<object>
		<name>shoe</name>
		<pose>Unspecified</pose>
		<truncated>0</truncated>
		<difficult>0</difficult>
		<bndbox>
			<xmin>464</xmin>
			<ymin>983</ymin>
			<xmax>960</xmax>
			<ymax>1194</ymax>
		</bndbox>
	</object>
	<object>
		<name>shoe</name>
		<pose>Unspecified</pose>
		<truncated>0</truncated>
		<difficult>0</difficult>
		<bndbox>
			<xmin>1427</xmin>
			<ymin>965</ymin>
			<xmax>1694</xmax>
			<ymax>1146</ymax>
		</bndbox>
	</object>
	<object>
		<name>shoe</name>
		<pose>Unspecified</pose>
		<truncated>0</truncated>
		<difficult>0</difficult>
		<bndbox>
			<xmin>1805</xmin>
			<ymin>1005</ymin>
			<xmax>2083</xmax>
			<ymax>1165</ymax>
		</bndbox>
	</object>
	<object>
		<name>shoe</name>
		<pose>Unspecified</pose>
		<truncated>0</truncated>
		<difficult>0</difficult>
		<bndbox>
			<xmin>2005</xmin>
			<ymin>931</ymin>
			<xmax>2605</xmax>
			<ymax>1224</ymax>
		</bndbox>
	</object>
	<object>
		<name>shoe</name>
		<pose>Unspecified</pose>
		<truncated>0</truncated>
		<difficult>0</difficult>
		<bndbox>
			<xmin>2894</xmin>
			<ymin>972</ymin>
			<xmax>3320</xmax>
			<ymax>1202</ymax>
		</bndbox>
	</object>
</annotation>